{
  "id": 40,
  "part": null,
  "page": 41,
  "number": null,
  "content": "<span data-type=\"title\" id=toc-26>٢٤ - الدُّعَاءُ بَعْدَ التَّشَهُّدِ الأَخِيرِ قَبْلَ السَّلاَمِ</span>\r٥٥ - (١) ((اللَّهُمَّ إِنِّي أَعُوذُ بِكَ مِنْ عَذَابِ الْقَبْرِ، وَمِنْ عَذَابِ جَهَنَّمَ، وَمِنْ فِتْنَةِ الْمَحْيَا وَالْمَمَاتِ، وَمِنْ شَرِّ فِتْنَةِ الْمَسِيحِ الدَّجَّالِ)) (١).\r٥٦ - (٢) ((اللَّهُمَّ إِنِّي أَعوذُ بِكَ مِنْ عَذَابِ الْقَبْرِ، وَأَعوذُ بِكَ مِنْ فِتْنَةِ الْمَسِيحِ الدَّجَّالِ، وَأَعوذُ بِكَ مِنْ فِتْنَةِ الْمَحْيَا وَالْمَمَاتِ. اللَّهُمَّ إِنِّي أَعوذُ بِكَ مِنَ الْمَأْثَمِ وَالْمَغْرَمِ)) (٢).",
  "footnotes": [
    {
      "number": 1,
      "text": "البخاري، ٢/ ١٠٢، برقم ١٣٧٧، ومسلم، ١/ ٤١٢، برقم ٥٨٨، واللفظ لمسلم."
    },
    {
      "number": 2,
      "text": "البخاري، ١/ ٢٠٢، برقم ٨٣٢، ومسلم، ١/ ٤١٢، برقم ٥٨٧."
    }
  ],
  "segments": [
    {
      "type": "title",
      "id": "40-t0",
      "titleId": 26,
      "content": "٢٤ - الدُّعَاءُ بَعْدَ التَّشَهُّدِ الأَخِيرِ قَبْلَ السَّلاَمِ",
      "sentences": [
        {
          "id": "40-t0-0",
          "text": "٢٤ - الدُّعَاءُ بَعْدَ التَّشَهُّدِ الأَخِيرِ قَبْلَ السَّلاَمِ"
        }
      ]
    },
    {
      "type": "text",
      "id": "40-s1",
      "content": "\r٥٥ - (١) ((اللَّهُمَّ إِنِّي أَعُوذُ بِكَ مِنْ عَذَابِ الْقَبْرِ، وَمِنْ عَذَابِ جَهَنَّمَ، وَمِنْ فِتْنَةِ الْمَحْيَا وَالْمَمَاتِ، وَمِنْ شَرِّ فِتْنَةِ الْمَسِيحِ الدَّجَّالِ)) (١).\r٥٦ - (٢) ((اللَّهُمَّ إِنِّي أَعوذُ بِكَ مِنْ عَذَابِ الْقَبْرِ، وَأَعوذُ بِكَ مِنْ فِتْنَةِ الْمَسِيحِ الدَّجَّالِ، وَأَعوذُ بِكَ مِنْ فِتْنَةِ الْمَحْيَا وَالْمَمَاتِ. اللَّهُمَّ إِنِّي أَعوذُ بِكَ مِنَ الْمَأْثَمِ وَالْمَغْرَمِ)) (٢).",
      "sentences": [
        {
          "id": "40-s1-0",
          "text": "٥٥ - (١) ((اللَّهُمَّ إِنِّي أَعُوذُ بِكَ مِنْ عَذَابِ الْقَبْرِ، وَمِنْ عَذَابِ جَهَنَّمَ، وَمِنْ فِتْنَةِ الْمَحْيَا وَالْمَمَاتِ، وَمِنْ شَرِّ فِتْنَةِ الْمَسِيحِ الدَّجَّالِ)) (١).٥٦ - (٢) ((اللَّهُمَّ إِنِّي أَعوذُ بِكَ مِنْ عَذَابِ الْقَبْرِ، وَأَعوذُ بِكَ مِنْ فِتْنَةِ الْمَسِيحِ الدَّجَّالِ، وَأَعوذُ بِكَ مِنْ فِتْنَةِ الْمَحْيَا وَالْمَمَاتِ. اللَّهُمَّ إِنِّي أَعوذُ بِكَ مِنَ الْمَأْثَمِ وَالْمَغْرَمِ)) (٢)."
        }
      ]
    }
  ],
  "titleId": 26,
  "titleText": null,
  "nextPagePreview": "٥٧ - (٣) ((اللَّهُمَّ إِنِّي ظَلَمْتُ نَفْسِي ظُلْماً كَثِيراً، وَلاَ يَغْفِرُ ا"
}