{
  "id": 52,
  "part": null,
  "page": 53,
  "number": null,
  "content": "- وَيُسَمِّي حَاجَتَهُ - خَيْرٌ لِي فِي دِينِي وَمَعَاشِي وَعَاقِبَةِ أَمْرِي - أَوْ قَالَ: عَاجِلِهِ وَآجِلِهِ - فَاقْدُرْهُ لِي وَيَسِّرْهُ لِي ثمَّ بَارِكْ لِي فِيهِ، وَإِنْ كُنْتَ تَعْلَمُ أَنَّ هَذَا الْأَمْرَ شَرٌّ لِي فِي دِينِي وَمَعَاشِي وَعَاقِبَةِ أَمْرِي - أَوْ قَالَ: عَاجِلِهِ وَآجِلِهِ - فَاصْرِفْهُ عَنِّي وَاصْرِفْنِي عَنْهُ وَاقْدُرْ لِيَ الْخَيْرَ حَيْثُ كَانَ، ثُمَّ أَرْضِنِي بِهِ)) (١).\rوَمَا نَدِمَ مَنِ اسْتَخَارَ الْخَالِقَ، وَشَاوَرَ الْمَخْلُوقِينَ الْمُؤْمِنِينَ وَتَثَبَّتَ فِي أَمْرِهِ،",
  "footnotes": [
    {
      "number": 1,
      "text": "البخاري، ٧/ ١٦٢، برقم ١١٦٢."
    }
  ],
  "segments": [
    {
      "type": "text",
      "id": "52-s0",
      "content": "- وَيُسَمِّي حَاجَتَهُ - خَيْرٌ لِي فِي دِينِي وَمَعَاشِي وَعَاقِبَةِ أَمْرِي - أَوْ قَالَ: عَاجِلِهِ وَآجِلِهِ - فَاقْدُرْهُ لِي وَيَسِّرْهُ لِي ثمَّ بَارِكْ لِي فِيهِ، وَإِنْ كُنْتَ تَعْلَمُ أَنَّ هَذَا الْأَمْرَ شَرٌّ لِي فِي دِينِي وَمَعَاشِي وَعَاقِبَةِ أَمْرِي - أَوْ قَالَ: عَاجِلِهِ وَآجِلِهِ - فَاصْرِفْهُ عَنِّي وَاصْرِفْنِي عَنْهُ وَاقْدُرْ لِيَ الْخَيْرَ حَيْثُ كَانَ، ثُمَّ أَرْضِنِي بِهِ)) (١).\rوَمَا نَدِمَ مَنِ اسْتَخَارَ الْخَالِقَ، وَشَاوَرَ الْمَخْلُوقِينَ الْمُؤْمِنِينَ وَتَثَبَّتَ فِي أَمْرِهِ،",
      "sentences": [
        {
          "id": "52-s0-0",
          "text": "- وَيُسَمِّي حَاجَتَهُ - خَيْرٌ لِي فِي دِينِي وَمَعَاشِي وَعَاقِبَةِ أَمْرِي - أَوْ قَالَ: عَاجِلِهِ وَآجِلِهِ - فَاقْدُرْهُ لِي وَيَسِّرْهُ لِي ثمَّ بَارِكْ لِي فِيهِ، وَإِنْ كُنْتَ تَعْلَمُ أَنَّ هَذَا الْأَمْرَ شَرٌّ لِي فِي دِينِي وَمَعَاشِي وَعَاقِبَةِ أَمْرِي - أَوْ قَالَ: عَاجِلِهِ وَآجِلِهِ - فَاصْرِفْهُ عَنِّي وَاصْرِفْنِي عَنْهُ وَاقْدُرْ لِيَ الْخَيْرَ حَيْثُ كَانَ، ثُمَّ أَرْضِنِي بِهِ)) (١).وَمَا نَدِمَ مَنِ اسْتَخَارَ الْخَالِقَ، وَشَاوَرَ الْمَخْلُوقِينَ الْمُؤْمِنِينَ وَتَثَبَّتَ فِي أَمْرِهِ،"
        }
      ]
    }
  ],
  "titleId": 28,
  "titleText": null,
  "continuedFromPreviousPage": true,
  "nextPagePreview": "فَقَدْ قَالَ اللَّهُ ﷾: ﴿وَشاوِرْهُمْ فِي الْأَمْرِ فَإِذَا عَزَمْتَ فَتَوَكَّلْ"
}